<?xml version="1.0" encoding="utf-8" ?><dwsync><file name=".DS_Store" server="dev.foundrydev.co.uk//srv/www/dev.foundrydev.co.uk/public_html/" local="3553166465" remote="12144835367" /><file name="kumho1a.jpg" server="dev.foundrydev.co.uk//srv/www/dev.foundrydev.co.uk/public_html/" local="3554899922" remote="-4611767069495297241" /><file name="kumho1b.jpg" server="dev.foundrydev.co.uk//srv/www/dev.foundrydev.co.uk/public_html/" local="3554899922" remote="-4611767069495297241" /><file name="kumho1c.jpg" server="dev.foundrydev.co.uk//srv/www/dev.foundrydev.co.uk/public_html/" local="3554899922" remote="12144835367" /><file name="kumho1c.svg" server="dev.foundrydev.co.uk//srv/www/dev.foundrydev.co.uk/public_html/" local="3553153196" remote="-4611767069495297241" /><file name="kumho2.jpg" server="dev.foundrydev.co.uk//srv/www/dev.foundrydev.co.uk/public_html/" local="3553153463" remote="-4611767069495297240" /><file name="kumho4.jpg" server="dev.foundrydev.co.uk//srv/www/dev.foundrydev.co.uk/public_html/" local="3554899922" remote="-4611731610245301464" /><file name="kumho5.jpg" server="dev.foundrydev.co.uk//srv/www/dev.foundrydev.co.uk/public_html/" local="3553157837" remote="-4611767069495297240" /><file name="kumho6a.jpg" server="dev.foundrydev.co.uk//srv/www/dev.foundrydev.co.uk/public_html/" local="3554899922" remote="-4611767069495297240" /><file name="kumho6b.jpg" server="dev.foundrydev.co.uk//srv/www/dev.foundrydev.co.uk/public_html/" local="3554899922" remote="-4611767069495297240" /><file name="kumho7a.jpg" server="dev.foundrydev.co.uk//srv/www/dev.foundrydev.co.uk/public_html/" local="3554899922" remote="-4611767069495297240" /><file name="kumho7b.jpg" server="dev.foundrydev.co.uk//srv/www/dev.foundrydev.co.uk/public_html/" local="3554899922" remote="-4611767069495297240" /><file name="kumho8a.png" server="dev.foundrydev.co.uk//srv/www/dev.foundrydev.co.uk/public_html/" local="3553166411" remote="-4611767069495297239" /><file name="kumho8b.png" server="dev.foundrydev.co.uk//srv/www/dev.foundrydev.co.uk/public_html/" local="3553166731" remote="-4611767069495297239" /><file name="kumho8c.png" server="dev.foundrydev.co.uk//srv/www/dev.foundrydev.co.uk/public_html/" local="3553166163" remote="-4611767069495297239" /><file name="kumho9a.png" server="dev.foundrydev.co.uk//srv/www/dev.foundrydev.co.uk/public_html/" local="3553169478" remote="-4611767069495297239" /><file name="kumho9b.png" server="dev.foundrydev.co.uk//srv/www/dev.foundrydev.co.uk/public_html/" local="3553169480" remote="-4611767069495297239" /><file name="kumho9c.png" server="dev.foundrydev.co.uk//srv/www/dev.foundrydev.co.uk/public_html/" local="3553169110" remote="-4611767069495297238" /><file name="kumho10.jpg" server="dev.foundrydev.co.uk//srv/www/dev.foundrydev.co.uk/public_html/" local="3554899922" remote="-4611767069495297241" /></dwsync>